qhyccd_capture/__init__.py
qhyccd_capture/accept_sdk_data.py
qhyccd_capture/astrometry.py
qhyccd_capture/auto_exposure.py
qhyccd_capture/auto_white_balance.py
qhyccd_capture/captureFrame.py
qhyccd_capture/control_id.py
qhyccd_capture/externalTriggerThread.py
qhyccd_capture/fits_header.py
qhyccd_capture/fits_header_defaults.py
qhyccd_capture/histogramWidget.py
qhyccd_capture/language.py
qhyccd_capture/memory_updated.py
qhyccd_capture/napari.yaml
qhyccd_capture/planned_shooting.py
qhyccd_capture/previewThread.py
qhyccd_capture/qhyccd_capture.py
qhyccd_capture/qhyccd_sdk.py
qhyccd_capture/read_raw_image.py
qhyccd_capture/save_video.py
qhyccd_capture/setting.py
qhyccd_capture/sharedMemoryManager.py
qhyccd_capture/stellarSolver.py
qhyccd_capture/icon/GPS_icon.png
qhyccd_capture/icon/camera_icon.png
qhyccd_capture/icon/film_icon.png
qhyccd_capture/icon/instagram_icon.png
qhyccd_capture/icon/thermometer_icon.png
qhyccd_capture/icon/toggle_right_icon.png
qhyccd_capture/icon/trigger_icon.png
qhyccd_capture/icon/video_icon.png
qhyccd_capture/images/image.png
qhyccd_capture-0.0.4.0.dist-info/METADATA
qhyccd_capture-0.0.4.0.dist-info/WHEEL
qhyccd_capture-0.0.4.0.dist-info/entry_points.txt
qhyccd_capture-0.0.4.0.dist-info/top_level.txt
qhyccd_capture-0.0.4.0.dist-info/RECORD
