Metadata-Version: 2.1
Name: qhyccd-capture
Version: 0.0.4.0
Summary: The basic operations for QHYCCD series cameras
Author: QHYCCD
Author-email: lq@qhyccd.com
Classifier: Development Status :: 2 - Pre-Alpha
Classifier: Framework :: napari
Classifier: Intended Audience :: Developers
Classifier: License :: OSI Approved :: BSD License
Classifier: Operating System :: OS Independent
Classifier: Programming Language :: Python
Classifier: Programming Language :: Python :: 3
Classifier: Programming Language :: Python :: 3 :: Only
Classifier: Programming Language :: Python :: 3.9
Classifier: Programming Language :: Python :: 3.10
Classifier: Programming Language :: Python :: 3.11
Classifier: Programming Language :: Python :: 3.12
Classifier: Topic :: Scientific/Engineering :: Image Processing
Requires-Python: >=3.9
Requires-Dist: numpy
Requires-Dist: magicgui
Requires-Dist: qtpy
Requires-Dist: opencv-python
Requires-Dist: PyQt5
Requires-Dist: matplotlib
Requires-Dist: astropy
Requires-Dist: psutil
Requires-Dist: photutils<1.14.0,>=1.11.0
Requires-Dist: pybind11
Requires-Dist: pyqtgraph
Provides-Extra: testing
Requires-Dist: tox; extra == "testing"
Requires-Dist: pytest; extra == "testing"
Requires-Dist: pytest-cov; extra == "testing"
Requires-Dist: pytest-qt; extra == "testing"
Requires-Dist: napari; extra == "testing"
